summarizer/__init__.py
summarizer/cli.py
summarizer/summarizer.py
summarizer/tests.ipynb
summarizer/utils.py
summarizer/webapp/app.py
summarizer/webapp/gradio_app.py
summarymaker-0.2.9.dist-info/LICENSE
summarymaker-0.2.9.dist-info/METADATA
summarymaker-0.2.9.dist-info/WHEEL
summarymaker-0.2.9.dist-info/entry_points.txt
summarymaker-0.2.9.dist-info/top_level.txt
summarymaker-0.2.9.dist-info/RECORD
