Metadata-Version: 2.2
Name: summarymaker
Version: 0.2.9
Summary: A command-line and web application tool for text summarization
Home-page: https://github.com/hwang2006/summarymaker
Author: Soonwook Hwang
Author-email: hwang@kisti.re.kr
Classifier: Programming Language :: Python :: 3
Classifier: License :: OSI Approved :: MIT License
Classifier: Operating System :: OS Independent
Requires-Python: >=3.7
License-File: LICENSE
Requires-Dist: click==8.1.8
Requires-Dist: transformers==4.48.0
Requires-Dist: torch==2.4.0
Requires-Dist: numpy==1.26.4
Requires-Dist: beautifulsoup4==4.12.3
Requires-Dist: requests==2.32.3
Requires-Dist: flask==3.1.0
Requires-Dist: gradio==5.12.0
Provides-Extra: dev
Requires-Dist: pytest>=7.0; extra == "dev"
Requires-Dist: pytest-cov>=4.0; extra == "dev"
Requires-Dist: pytest-mock>=3.10.0; extra == "dev"
Requires-Dist: requests-mock>=1.11.0; extra == "dev"
Requires-Dist: black>=22.0.0; extra == "dev"
Requires-Dist: twine>=4.0.0; extra == "dev"
Requires-Dist: build>=0.10.0; extra == "dev"
Requires-Dist: wheel>=0.36.0; extra == "dev"
Dynamic: author
Dynamic: author-email
Dynamic: classifier
Dynamic: description
Dynamic: description-content-type
Dynamic: home-page
Dynamic: provides-extra
Dynamic: requires-dist
Dynamic: requires-python
Dynamic: summary
